Metadata-Version: 1.1
Name: librarymayaasciikkn
Version: 0.0.1
Summary: Functions for parsing of maya ascii files that returns name, position and uid of all mesh objects
Home-page: UNKNOWN
Author: Katarina Knezevic
Author-email: kvknezevic@gmial.com
License: MIT
Keywords: maya ascii
Platform: UNKNOWN
Classifier: Development Status :: 5 - Production/Stable
Classifier: Intended Audience :: Education
Classifier: Operating System :: Microsoft :: Windows :: Windows 10
Classifier: License :: OSI Approved :: MIT License
Classifier: Programming Language :: Python :: 2
